AppMainAndGUI/MainMenu.py
AppMainAndGUI/__init__.py
AppMainAndGUI/tempCodeRunnerFile.py
TelloControlModule/Initial_setup.py
TelloControlModule/TellControlMain.py
TelloControlModule/__init__.py
TelloControlModule/adding_flip_buttons.py
TelloControlModule/adding_set_speed_bar.py
TelloControlModule/adding_videostream.py
TelloControlModule/flight_commands.py
TelloControlModule/indicators.py
TelloControlModule/main.py
TelloControlModule/record_tello.py
TelloControlModule/take_pictures.py
TelloControlModule/tello.py
TelloControlModule/tkinter_keyboard_controller.py
adaptivedrone-0.1.0.dist-info/METADATA
adaptivedrone-0.1.0.dist-info/WHEEL
adaptivedrone-0.1.0.dist-info/entry_points.txt
adaptivedrone-0.1.0.dist-info/top_level.txt
adaptivedrone-0.1.0.dist-info/RECORD
