Metadata-Version: 2.4
Name: AdaptiveDrone
Version: 0.1.0
Summary: Drone app with face gesture and GUI control
Home-page: https://github.com/Abumere17/AdaptiveDrone
Author: Abumere, Himadri, Tejas, Daniel
Author-email: Abumere_Okhihan@student.uml.edu
Classifier: Programming Language :: Python :: 3
Classifier: License :: OSI Approved :: MIT License
Classifier: Operating System :: OS Independent
Requires-Python: >=3.8
Requires-Dist: djitellopy
Requires-Dist: opencv-python
Requires-Dist: mediapipe
Requires-Dist: tk
Requires-Dist: numpy
Dynamic: author
Dynamic: author-email
Dynamic: classifier
Dynamic: description
Dynamic: description-content-type
Dynamic: home-page
Dynamic: requires-dist
Dynamic: requires-python
Dynamic: summary
